ewt/__init__.py
ewt/cli.py
ewt/generator.py
ewt/templates/__init__.py
ewt/templates/index.html
ewt_gen-1.3.1.dist-info/METADATA
ewt_gen-1.3.1.dist-info/WHEEL
ewt_gen-1.3.1.dist-info/entry_points.txt
ewt_gen-1.3.1.dist-info/RECORD
