Metadata-Version: 2.4
Name: ewt-gen
Version: 1.3.1
Summary: Generate static websites for ESPHome firmware distribution using ESP Web Tools
Project-URL: Homepage, https://github.com/esphome/ewt-gen
Project-URL: Repository, https://github.com/esphome/ewt-gen
Project-URL: Issues, https://github.com/esphome/ewt-gen/issues
License-Expression: Apache-2.0
Keywords: esp32,esp8266,esphome,firmware,web-tools
Classifier: Development Status :: 4 - Beta
Classifier: Environment :: Console
Classifier: Intended Audience :: Developers
Classifier: License :: OSI Approved :: Apache Software License
Classifier: Programming Language :: Python :: 3
Classifier: Programming Language :: Python :: 3.10
Classifier: Programming Language :: Python :: 3.11
Classifier: Programming Language :: Python :: 3.12
Classifier: Programming Language :: Python :: 3.13
Classifier: Topic :: Home Automation
Requires-Python: >=3.10
Requires-Dist: click>=8.0
Requires-Dist: pyyaml>=6.0
